excel_validator/__init__.py
excel_validator/_version.py
excel_validator/config.ini
excel_validator/config.json
excel_validator/functions.py
excel_validator/report.py
excel_validator/validator.py
excel_validator/webservice.py
excel_validator/config/agent/historical/config.json
excel_validator/config/agent/historical/plugins/agentIdValidationPlugin.py
excel_validator/config/agent/historical/plugins/agentRequiredRowValuesPlugin.py
excel_validator/config/agent/historical/plugins/agentRequiredRowsPlugin.py
excel_validator/config/agent/historical/schema/experiment.schema.json
excel_validator/config/agent/historical/schema/observedScores.checklist.json
excel_validator/config/agent/historical/schema/observedScores.schema.json
excel_validator/config/agent/historical/schema/rangeOfValues.schema.json
excel_validator/config/agent/historical/schema/trait.checklist.json
excel_validator/config/agent/historical/schema/trait.schema.json
excel_validator/config/agent/precision/config.json
excel_validator/config/agent/precision/plugins/agentIdValidationPlugin.py
excel_validator/config/agent/precision/schema/2a_study.schema.json
excel_validator/config/agent/precision/schema/2c_treatments.schema.json
excel_validator/config/agent/precision/schema/3a_observation_variables.schema.json
excel_validator/config/agent/precision/schema/3b_rating_scores.schema.json
excel_validator/config/agent/precision/schema/3c_valid_ranges.schema.json
excel_validator/config/agent/precision/schema/4a_observed_values.checklist.json
excel_validator/config/agent/precision/schema/4a_observed_values.schema.json
excel_validator/config/default/config.json
excel_validator/config/miappe/config.json
excel_validator/config/miappe/plugins/testPlugin.py
excel_validator/config/miappe/schema/biologicalmaterial.checklist.json
excel_validator/config/miappe/schema/biologicalmaterial.schema.json
excel_validator/config/miappe/schema/biologicalmaterial2study.pipeline.json
excel_validator-0.9.4.dist-info/licenses/LICENSE
excel_validator-0.9.4.dist-info/METADATA
excel_validator-0.9.4.dist-info/WHEEL
excel_validator-0.9.4.dist-info/entry_points.txt
excel_validator-0.9.4.dist-info/top_level.txt
excel_validator-0.9.4.dist-info/RECORD
