Metadata-Version: 2.4
Name: excel-validator
Version: 0.9.4
Summary: Validation of template based Excel files
Author-email: Matthijs Brouwer <matthijs.brouwer@wur.nl>
License: MIT License
Project-URL: Homepage, https://github.com/matthijsbrouwer/excel-validator
Classifier: Topic :: Internet :: Proxy Servers
Classifier: Topic :: Scientific/Engineering :: Bio-Informatics
Classifier: Programming Language :: Python :: 3.11
Classifier: Operating System :: OS Independent
Requires-Python: >=3.11
License-File: LICENSE
Requires-Dist: attrs==25.4.0
Requires-Dist: cachelib==0.13.0
Requires-Dist: Flask==3.1.2
Requires-Dist: flask_session==0.8.0
Requires-Dist: frictionless==5.18.1
Requires-Dist: func_timeout==4.3.5
Requires-Dist: jsonschema==4.25.1
Requires-Dist: numpy==2.3.4
Requires-Dist: openpyxl==3.1.5
Requires-Dist: pandas==2.3.3
Requires-Dist: Requests==2.32.5
Requires-Dist: rich==14.2.0
Requires-Dist: tqdm==4.67.1
Requires-Dist: waitress==3.0.2
Dynamic: license-file
